{"D": 6, "I": 4, "S": 5, "V": 2, "F": 1000, "streets": [{"start_junction": 2, "end_junction": 0, "name": "rue-de-londres", "length": 1}, {"start_junction": 0, "end_junction": 1, "name": "rue-d-amsterdam", "length": 1}, {"start_junction": 3, "end_junction": 1, "name": "rue-d-athenes", "length": 1}, {"start_junction": 2, "end_junction": 3, "name": "rue-de-rome", "length": 2}, {"start_junction": 1, "end_junction": 2, "name": "rue-de-moscou", "length": 3}], "paths": [["rue-de-londres", "rue-d-amsterdam", "rue-de-moscou", "rue-de-rome"], ["rue-d-athenes", "rue-de-moscou", "rue-de-londres"]]}